psh_pytorch/__init__.py
psh_pytorch/psh.py
psh_pytorch/utils.py
psh_pytorch-0.0.3.dist-info/LICENSE
psh_pytorch-0.0.3.dist-info/METADATA
psh_pytorch-0.0.3.dist-info/WHEEL
psh_pytorch-0.0.3.dist-info/top_level.txt
psh_pytorch-0.0.3.dist-info/RECORD
