Metadata-Version: 2.1
Name: psh-pytorch
Version: 0.0.3
Summary: Perfect Spatial Hashing in PyTorch
Author-email: David Li <david@davidl.me>
Project-URL: Homepage, https://github.com/dli7319/psh-pytorch
Project-URL: Bug Tracker, https://github.com/dli7319/psh-pytorch/issues
Classifier: Programming Language :: Python :: 3
Classifier: License :: OSI Approved :: MIT License
Classifier: Operating System :: OS Independent
Requires-Python: >=3.7
License-File: LICENSE
Requires-Dist: torch
Requires-Dist: numpy
Requires-Dist: tqdm
